devxhub_python/VERSION.txt
devxhub_python/__init__.py
devxhub_python/__main__.py
devxhub_python/cli.py
devxhub_python/config.py
devxhub_python/environment.py
devxhub_python/exceptions.py
devxhub_python/extensions.py
devxhub_python/find.py
devxhub_python/generate.py
devxhub_python/hooks.py
devxhub_python/log.py
devxhub_python/main.py
devxhub_python/prompt.py
devxhub_python/replay.py
devxhub_python/repository.py
devxhub_python/utils.py
devxhub_python/vcs.py
devxhub_python/zipfile.py
devxhub_python-0.5.0.dist-info/LICENSE.md
devxhub_python-0.5.0.dist-info/METADATA
devxhub_python-0.5.0.dist-info/WHEEL
devxhub_python-0.5.0.dist-info/entry_points.txt
devxhub_python-0.5.0.dist-info/top_level.txt
devxhub_python-0.5.0.dist-info/RECORD
